P4/P4Judger/src/def.v
//------------- Definition of GRFWDSel -------------
`define WDSel_aluans    2'b00
`define WDSel_dmrd      2'b01
`define WDSel_pc4       2'b10

//------------- Definition of GRFA3Sel -------------
`define A3Sel_rd    2'b00
`define A3Sel_rt    2'b01
`define A3Sel_ra    2'b10

//------------- Definition of ALUBSel -------------
`define BSel_rt    1'b0
`define BSel_imm   1'b1

//------------- Definition of DMOp -------------
`define DM_w    3'b000
`define DM_h    3'b001
`define DM_hu   3'b010
`define DM_b    3'b011
`define DM_bu   3'b100 

//------------- Definition of ALUOp -------------
`define ALU_add     4'b0000
`define ALU_sub     4'b0001
`define ALU_or      4'b0010
`define ALU_slt     4'b0011
//`define ALU_xor     4'b0100
`define ALU_lui     4'b0101
//`define ALU_sll     4'b0110
//`define ALU_srl     4'b0111
//`define ALU_sra     4'b0100
//`define ALU_srlv  4'b1001
//`define ALU_sllv  4'b0111
//`define ALU_srav  4'b1011

//------------- Definition of EXTOp -------------
`define EXT_sign    1'b1
`define EXT_unsign  1'b0

//------------- Definition of CMPOp -------------
`define CMP_beq     3'b000
//`define CMP_bltz    3'b001
//`define CMP_bgtz  3'b010
//`define CMP_bne     3'b011
//`define CMP_bgez  3'b100
//`define CMP_blez  3'b101

//------------- Definition of NPCOp -------------
`define NPC_pc4     3'b000
`define NPC_j_jal   3'b001
`define NPC_jr_jalr 3'b010
`define NPC_b       3'b011

//------------- Definition of Instruction opcode and funct -------------

// ** Arithmetic Logic Unit **
`define op_ADDU     6'b000000
`define fun_ADDU    6'b100001

`define op_SUBU     6'b000000
`define fun_SUBU    6'b100011

`define op_SLT      6'b000000
`define fun_SLT     6'b101010

`define op_ORI      6'b001101
`define op_LUI      6'b001111

// ** Shifter **
//`define op_SLL      6'b000000
// All Zero...

// ** Branch **
`define op_BEQ      6'b000100
`define op_J        6'b000010
`define op_JAL      6'b000011

`define op_JR       6'b000000
`define fun_JR      6'b001000

//`define op_JALR   6'b000000
//`define fun_JALR  6'b001001

// ** Memory Access **
`define op_LB       6'b100000
`define op_SB       6'b101000
`define op_LH       6'b100001
`define op_SH       6'b101001
`define op_LW       6'b100011
`define op_SW       6'b101011
`define op_LBU      6'b100100
`define op_LHU      6'b100101

P4/P4Judger/src/CTRL.v
`timescale 1ns / 1ps

`include "def.v"

module CTRL(
    input [31:0] Instr,
    input jump,
    //input overflow,

    output [4:0] rt,
    output [4:0] rs,
    output [4:0] rd,
    output [4:0] shamt,
    output [15:0] imm16,
    output [25:0] imm26,

    output [3:0] ALUOp,
    output [2:0] CMPOp,
    output [2:0] DMOp,
    output [1:0] GRFA3Sel,
    output [1:0] GRFWDSel,
    output ALUBSel,
    output DMWrEn,
    output EXTOp,
    output GRFWrEn,
    output [2:0] NPCOp
    );

    wire [5:0] opcode = Instr[31:26];
    wire [5:0] funct = Instr[5:0];
    assign rs = Instr[25:21];
    assign rt = Instr[20:16];
    assign rd = Instr[15:11];
    assign imm16 = Instr[15:0];
    assign imm26 = Instr[25:0];
    assign shamt = Instr[10:6];

    wire addu = (opcode == `op_ADDU && funct == `fun_ADDU);
    wire subu = (opcode == `op_SUBU && funct == `fun_SUBU);
    wire ori = (opcode == `op_ORI);
    wire lui = (opcode == `op_LUI);
    wire lw = (opcode == `op_LW);
    wire sw = (opcode == `op_SW);
    wire beq = (opcode == `op_BEQ);
    wire j = (opcode == `op_J);
    wire jal = (opcode == `op_JAL);
    wire jr = (opcode == `op_JR && funct == `fun_JR);
    wire lb = (opcode == `op_LB);
    wire sb = (opcode == `op_SB);
    wire lh = (opcode == `op_LH);
    wire sh = (opcode == `op_SH);
    wire lbu = (opcode == `op_LBU);
    wire lhu = (opcode == `op_LHU);
    wire slt = (opcode == `op_SLT && funct == `fun_SLT);

    assign ALUOp = (addu | lw | sw | lh | sh | lb | sb | lbu | lhu) ? `ALU_add :
                   (subu) ? `ALU_sub :
                   (ori) ? `ALU_or :
                   (lui) ? `ALU_lui :
                   (slt) ? `ALU_slt :
                   4'b0000;
    assign EXTOp = (beq | sw | lw | sh | lh | sb | lb | lbu | lhu) ? `EXT_sign :
                   `EXT_unsign;
    assign CMPOp = (beq) ? `CMP_beq :
                   3'b000;
    assign NPCOp = (beq) ? `NPC_b :
                   (j | jal) ? `NPC_j_jal :
                   (jr) ? `NPC_jr_jalr :
                   `NPC_pc4;
    assign DMOp = (lw | sw) ? `DM_w :
                  (lh | sh) ? `DM_h :
                  (lb | sb) ? `DM_b :
                  (lhu) ? `DM_hu :
                  `DM_bu;
    assign GRFWrEn = !(sw | beq | j | sh | sb | jr);
    assign DMWrEn = (sw | sb | sw);
    assign GRFWDSel = (jal) ? `WDSel_pc4 :
                      (lw) ? `WDSel_dmrd :
                      `WDSel_aluans;
    assign GRFA3Sel = (addu | subu | slt) ? `A3Sel_rd :
                      (jal) ? `A3Sel_ra :
                      `A3Sel_rt;
    assign ALUBSel = (addu | subu) ? `BSel_rt :
                     `BSel_imm;
endmodule

P4/P4_Source_Code/EXT.v
`timescale 1ns / 1ps

`include "def.v"

module EXT(
    input [15:0] imm16,
    input EXTOp,
    output [31:0] out32
    );

    assign out32 = (EXTOp == `EXT_sign) ? {{16{imm16[15]}}, imm16} :
                   (EXTOp == `EXT_unsign) ? {{16{1'b0}}, imm16} :
                   32'h0000_0000;

endmodule

P4/P4_Source_Code/DM.v
`timescale 1ns / 1ps

`include "def.v"

`define word            mem[Addr[11:2]]
`define half_word       mem[Addr[11:2]][(15+Addr[1]*16) -: 16]
`define byte            mem[Addr[11:2]][(7+Addr[1:0]*8) -: 8]
`define byte_sign       mem[Addr[11:2]][(7+Addr[1:0]*8)]
`define half_word_sign  mem[Addr[11:2]][(15+Addr[1]*16)]

module DM(
    input [31:0] Addr,
    input [31:0] WD,
    input [31:0] PC,
    input DMWrEn,
    input [2:0] DMOp,
    input clk,
    input reset,
    output [31:0] RD
    );

    reg[31:0] mem[0:1023];
    integer i;

    initial begin
        for(i = 0; i < 1024; i=i+1)
            mem[i] = 32'h0000_0000;
    end

    always @(posedge clk) begin
        if(reset) begin
            for(i = 0; i < 1024; i=i+1)
                mem[i] <= 32'h0000_0000;
        end else if(DMWrEn) begin
            case(DMOp)
                `DM_b: begin
                    `byte <= WD[7:0];
                    case(Addr[1:0])
                        2'b00: $display("@%h: *%h <= %h", PC, Addr, {mem[Addr[11:2]][31:8], WD[7:0]});
                        2'b01: $display("@%h: *%h <= %h", PC, Addr, {mem[Addr[11:2]][31:16], WD[7:0], mem[Addr[11:2]][7:0]});
                        2'b10: $display("@%h: *%h <= %h", PC, Addr, {mem[Addr[11:2]][31:24], WD[7:0], mem[Addr[11:2]][15:0]});
                        2'b11: $display("@%h: *%h <= %h", PC, Addr, {WD[7:0], mem[Addr[11:2]][23:0]});
                    endcase
                end
                `DM_h: begin
                    `half_word <= WD[15:0];
                    case(Addr[1])
                        1'b0: $display("@%h: *%h <= %h", PC, Addr, {mem[Addr[11:2]][31:16], WD[15:0]});
                        1'b1: $display("@%h: *%h <= %h", PC, Addr, {WD[15:0], mem[Addr[11:2]][15:0]});
                    endcase
                end
                `DM_w: begin
                    `word <= WD;
                    $display("@%h: *%h <= %h", PC, Addr, WD);
                end
                default: `word <= WD;
            endcase
        end
    end

    assign RD = (DMOp == `DM_b) ? {{24{`byte_sign}}, `byte} :
                (DMOp == `DM_bu) ? {{24{1'b0}}, `byte} :
                (DMOp == `DM_h) ? {{16{`half_word_sign}}, `half_word} :
                (DMOp == `DM_hu) ? {{16{1'b0}}, `half_word} :
                (DMOp == `DM_w) ? `word :
                32'h0000_0000;
endmodule

P4/P4_Source_Code/ALU.v
`timescale 1ns / 1ps

`include "def.v"

module ALU(
    input [31:0] A,
    input [31:0] B,
    input [3:0] ALUOp,
    input [4:0] shamt,
    //output reg overflow,
    output reg [31:0] C
    );

    always @(*) begin
        case(ALUOp)
            `ALU_add: C = A + B;
            `ALU_sub: C = A - B;
            `ALU_or: C = A | B;
            //`ALU_and: C = A & B;
            //`ALU_xor: C = A ^ B;
            `ALU_slt: C = ($signed(A) < $signed(B)) ? 32'b1 : 32'b0;
            //`ALU_srl: C = B >> shamt;
            //`ALU_sra: C = $signed($signed(B) >> shamt);
            `ALU_lui: C = B << 16;

            // Ready for add other instructions...

            default: C = 32'h0000_0000;
        endcase
    end

endmodule

P4/P4Judger/src/GRF.v
`timescale 1ns / 1ps

`include "def.v"

module GRF(
    input [4:0] A1,
    input [4:0] A2,
    input [4:0] A3,
    input [31:0] WD,
    input [31:0] PC,
    input GRFWrEn,
    input reset,
    input clk,
    output [31:0] RD1,
    output [31:0] RD2
    );

    reg [31:0] rf[0:31];
    integer i;
    reg[31:0] WrData;

    initial begin
        for(i = 0; i < 32; i=i+1)
            rf[i] = 32'h00000000;
    end

    always @(posedge clk) begin
        if(reset) begin
            for(i = 0; i < 32; i=i+1)
                rf[i] <= 32'h00000000;
        end else if(GRFWrEn) begin
            WrData = (A3 != 5'b00000) ? WD : 32'h0000_0000;
            rf[A3] <= WrData;
            if(A3 != 5'b00000)
				$display("@%h: $%d <= %h", PC, A3, WrData);
        end
    end

    assign RD1 = rf[A1];
    assign RD2 = rf[A2];

endmodule

P4/P4Judger/src/CMP.v
`timescale 1ns / 1ps

`include "def.v"

module CMP(
    input [31:0] rs,
    input [31:0] rt,
    input [2:0] CMPOp,
    output jump
    );

    wire eq = (rs == rt);
    wire ne = !eq;
    wire le0 = (rs < 0);
    wire ge0 = (rs > 0);
    wire eq0 = (rs == 0);

    assign jump = (CMPOp == `CMP_beq && eq) ? 1 :
                  0;

endmodule

P4/P4Judger/src/NPC.v
`timescale 1ns / 1ps

`include "def.v"

module NPC(
    input [31:0] PC,
    input [25:0] imm26,
    input [15:0] imm16,
    input [31:0] rs,
    input jump,
    input [2:0] NPCOp,
    output [31:0] PC4,
    output [31:0] NPC
    );

    assign PC4 = PC + 4;

    assign NPC = (NPCOp == `NPC_pc4) ? (PC + 4) :
                 (NPCOp == `NPC_j_jal) ? {PC[31:28], imm26, 2'b00} :
                 (NPCOp == `NPC_jr_jalr) ? rs :
                 (NPCOp == `NPC_b && jump) ? (PC + 4 + {{14{imm16[15]}}, imm16, 2'b00}) :
                 PC4;

endmodule

P4/P4Judger/src/IFU.v
`timescale 1ns / 1ps

`include "def.v"

module IFU(
    input reset,
    input clk,
    input [31:0] NPC,
    output reg[31:0] PC,
    output [31:0] Instr
    );

    reg[31:0] rom[0:1023];

    initial begin
        $readmemh("code.txt", rom);
        PC = 32'h0000_3000;
    end

    always @(posedge clk) begin
        if(reset) begin
            PC <= 32'h0000_3000;
        end else begin
            PC <= NPC;
        end
    end

    assign Instr = rom[PC[11:2]];
endmodule

P4/P4Judger/src/mips.v
`timescale 1ns / 1ps
`include "def.v"
`include "ALU.v"
`include "CTRL.v"
`include "DM.v"
`include "GRF.v"
`include "IFU.v"
`include "CMP.v"
`include "EXT.v"
`include "NPC.v"
//////////////////////////////////////////////////////////////////////////////////
// Company: 
// Engineer: 
// 
// Create Date:    11:46:54 11/12/2021 
// Design Name: 
// Module Name:    mips 
// Project Name: 
// Target Devices: 
// Tool versions: 
// Description: 
//
// Dependencies: 
//
// Revision: 
// Revision 0.01 - File Created
// Additional Comments: 
//
//////////////////////////////////////////////////////////////////////////////////
module mips(
    input clk,
    input reset
    );

    wire[4:0] addr_rt, addr_rd, addr_rs, shamt;
    wire[15:0] imm16;
    wire[25:0] imm26;
    wire[31:0] imm32;
    wire[31:0] pc, npc, pc4;
    wire[31:0] grf_rd1, grf_rd2;
    wire[31:0] alu_ans;
    wire[31:0] dm_rd;
    wire[31:0] instr;

    wire jump;
    //wire overflow;
    wire[3:0] ALUOp;
    wire[2:0] CMPOp;
    wire[2:0] DMOp;
    wire[1:0] GRFA3Sel, GRFWDSel;
    wire ALUBSel, DMWrEn, EXTOp, GRFWrEn;
    wire[2:0] NPCOp;

    IFU _ifu(
        .reset(reset),
        .clk(clk),
        .NPC(npc),
        .PC(pc),
        .Instr(instr)
    );

    NPC _npc(
        .PC(pc),
        .imm26(imm26),
        .imm16(imm16),
        .rs(grf_rd1),
        .jump(jump),
        .NPCOp(NPCOp),
        .PC4(pc4),
        .NPC(npc)
    );

    CMP _cmp(
        .rs(grf_rd1),
        .rt(grf_rd2),
        .CMPOp(CMPOp),
        .jump(jump)
    );

    GRF _grf(
        .A1(addr_rs),
        .A2(addr_rt),
        .A3(
            (GRFA3Sel == `A3Sel_ra) ? 5'd31 :
            (GRFA3Sel == `A3Sel_rt) ? addr_rt : addr_rd
        ),
        .WD(
            (GRFWDSel == `WDSel_pc4) ? pc4 :
            (GRFWDSel == `WDSel_dmrd) ? dm_rd : alu_ans
        ),
        .PC(pc),
        .GRFWrEn(GRFWrEn),
        .reset(reset),
        .clk(clk),
        .RD1(grf_rd1),
        .RD2(grf_rd2)
    );

    ALU _alu(
        .A(grf_rd1),
        .B(
            (ALUBSel == `BSel_rt) ? grf_rd2 : imm32
        ),
        .ALUOp(ALUOp),
        .shamt(shamt),
        //.overflow(overflow),
        .C(alu_ans)
    );

    DM _dm(
        .Addr(alu_ans),
        .WD(grf_rd2),
        .PC(pc),
        .DMWrEn(DMWrEn),
        .DMOp(DMOp),
        .clk(clk),
        .reset(reset),
        .RD(dm_rd)
    );

    EXT _ext(
        .imm16(imm16),
        .EXTOp(EXTOp),
        .out32(imm32)
    );

    CTRL _ctrl(
        .Instr(instr),
        .jump(jump),
        //.overflow(overflow)
        .rt(addr_rt),
        .rs(addr_rs),
        .rd(addr_rd),
        .shamt(shamt),
        .imm16(imm16),
        .imm26(imm26),
        .ALUOp(ALUOp),
        .CMPOp(CMPOp),
        .DMOp(DMOp),
        .GRFA3Sel(GRFA3Sel),
        .GRFWDSel(GRFWDSel),
        .ALUBSel(ALUBSel),
        .DMWrEn(DMWrEn),
        .EXTOp(EXTOp),
        .GRFWrEn(GRFWrEn),
        .NPCOp(NPCOp)
    );

endmodule

P4/P4Judger/src/mips_tb.v
`timescale 1ns / 1ps
`include "mips.v"
////////////////////////////////////////////////////////////////////////////////
// Company: 
// Engineer:
//
// Create Date:   19:25:35 11/12/2021
// Design Name:   mips
// Module Name:   G:/MyWorkspace/Computer_Organization/P4/P4_L0_CPU/mips_tb.v
// Project Name:  P4_L0_CPU
// Target Device:  
// Tool versions:  
// Description: 
//
// Verilog Test Fixture created by ISE for module: mips
//
// Dependencies:
// 
// Revision:
// Revision 0.01 - File Created
// Additional Comments:
// 
////////////////////////////////////////////////////////////////////////////////

module mips_tb;

	// Inputs
	reg clk;
	reg reset;

	// Instantiate the Unit Under Test (UUT)
	mips uut (
		.clk(clk), 
		.reset(reset)
	);

	always #1 clk = ~clk;

	initial begin
		$dumpfile("mips_tb.vcd");
		$dumpvars;
		// Initialize Inputs
		clk = 0;
		reset = 1;

		#10;
		reset = 0;
        #4096;
		$finish;
		// Add stimulus here

	end
      
endmodule

P4/P4Judger/src/mips_tb.vcd
$date
	Wed Nov 17 17:19:06 2021
$end
$version
	Icarus Verilog
$end
$timescale
	1ps
$end
$scope module mips_tb $end
$var reg 1 ! clk $end
$var reg 1 " reset $end
$scope module uut $end
$var wire 1 ! clk $end
$var wire 1 " reset $end
$var wire 5 # shamt [4:0] $end
$var wire 32 $ pc4 [31:0] $end
$var wire 32 % pc [31:0] $end
$var wire 32 & npc [31:0] $end
$var wire 1 ' jump $end
$var wire 32 ( instr [31:0] $end
$var wire 32 ) imm32 [31:0] $end
$var wire 26 * imm26 [25:0] $end
$var wire 16 + imm16 [15:0] $end
$var wire 32 , grf_rd2 [31:0] $end
$var wire 32 - grf_rd1 [31:0] $end
$var wire 32 . dm_rd [31:0] $end
$var wire 32 / alu_ans [31:0] $end
$var wire 5 0 addr_rt [4:0] $end
$var wire 5 1 addr_rs [4:0] $end
$var wire 5 2 addr_rd [4:0] $end
$var wire 3 3 NPCOp [2:0] $end
$var wire 1 4 GRFWrEn $end
$var wire 2 5 GRFWDSel [1:0] $end
$var wire 2 6 GRFA3Sel [1:0] $end
$var wire 1 7 EXTOp $end
$var wire 1 8 DMWrEn $end
$var wire 3 9 DMOp [2:0] $end
$var wire 3 : CMPOp [2:0] $end
$var wire 4 ; ALUOp [3:0] $end
$var wire 1 < ALUBSel $end
$scope module _alu $end
$var wire 32 = B [31:0] $end
$var wire 5 > shamt [4:0] $end
$var wire 4 ? ALUOp [3:0] $end
$var wire 32 @ A [31:0] $end
$var reg 32 A C [31:0] $end
$upscope $end
$scope module _cmp $end
$var wire 32 B rt [31:0] $end
$var wire 32 C rs [31:0] $end
$var wire 1 D ne $end
$var wire 1 E le0 $end
$var wire 1 ' jump $end
$var wire 1 F ge0 $end
$var wire 1 G eq0 $end
$var wire 1 H eq $end
$var wire 3 I CMPOp [2:0] $end
$upscope $end
$scope module _ctrl $end
$var wire 1 8 DMWrEn $end
$var wire 1 J addu $end
$var wire 1 K jr $end
$var wire 1 ' jump $end
$var wire 1 L slt $end
$var wire 1 M subu $end
$var wire 1 N sw $end
$var wire 5 O shamt [4:0] $end
$var wire 1 P sh $end
$var wire 1 Q sb $end
$var wire 5 R rt [4:0] $end
$var wire 5 S rs [4:0] $end
$var wire 5 T rd [4:0] $end
$var wire 1 U ori $end
$var wire 6 V opcode [5:0] $end
$var wire 1 W lw $end
$var wire 1 X lui $end
$var wire 1 Y lhu $end
$var wire 1 Z lh $end
$var wire 1 [ lbu $end
$var wire 1 \ lb $end
$var wire 1 ] jal $end
$var wire 1 ^ j $end
$var wire 26 _ imm26 [25:0] $end
$var wire 16 ` imm16 [15:0] $end
$var wire 6 a funct [5:0] $end
$var wire 1 b beq $end
$var wire 3 c NPCOp [2:0] $end
$var wire 32 d Instr [31:0] $end
$var wire 1 4 GRFWrEn $end
$var wire 2 e GRFWDSel [1:0] $end
$var wire 2 f GRFA3Sel [1:0] $end
$var wire 1 7 EXTOp $end
$var wire 3 g DMOp [2:0] $end
$var wire 3 h CMPOp [2:0] $end
$var wire 4 i ALUOp [3:0] $end
$var wire 1 < ALUBSel $end
$upscope $end
$scope module _dm $end
$var wire 32 j Addr [31:0] $end
$var wire 3 k DMOp [2:0] $end
$var wire 1 8 DMWrEn $end
$var wire 1 ! clk $end
$var wire 1 " reset $end
$var wire 32 l WD [31:0] $end
$var wire 32 m RD [31:0] $end
$var wire 32 n PC [31:0] $end
$var integer 32 o i [31:0] $end
$upscope $end
$scope module _ext $end
$var wire 1 7 EXTOp $end
$var wire 16 p imm16 [15:0] $end
$var wire 32 q out32 [31:0] $end
$upscope $end
$scope module _grf $end
$var wire 5 r A1 [4:0] $end
$var wire 5 s A2 [4:0] $end
$var wire 5 t A3 [4:0] $end
$var wire 1 4 GRFWrEn $end
$var wire 32 u RD1 [31:0] $end
$var wire 32 v RD2 [31:0] $end
$var wire 32 w WD [31:0] $end
$var wire 1 ! clk $end
$var wire 1 " reset $end
$var wire 32 x PC [31:0] $end
$var reg 32 y WrData [31:0] $end
$var integer 32 z i [31:0] $end
$upscope $end
$scope module _ifu $end
$var wire 32 { Instr [31:0] $end
$var wire 1 ! clk $end
$var wire 1 " reset $end
$var wire 32 | NPC [31:0] $end
$var reg 32 } PC [31:0] $end
$upscope $end
$scope module _npc $end
$var wire 3 ~ NPCOp [2:0] $end
$var wire 32 !" PC [31:0] $end
$var wire 16 "" imm16 [15:0] $end
$var wire 26 #" imm26 [25:0] $end
$var wire 1 ' jump $end
$var wire 32 $" rs [31:0] $end
$var wire 32 %" PC4 [31:0] $end
$var wire 32 &" NPC [31:0] $end
$upscope $end
$upscope $end
$upscope $end
$enddefinitions $end
#0
$dumpvars
b11000000000100 &"
b11000000000100 %"
b0 $"
b11111111111111100000100011 #"
b1111100000100011 ""
b11000000000000 !"
b0 ~
b11000000000000 }
b11000000000100 |
b11111111111111100000100011 {
b100000 z
bx y
b11000000000000 x
b0 w
b0 v
b0 u
b11111 t
b11111 s
b11111 r
b1111100000100011 q
b1111100000100011 p
b10000000000 o
b11000000000000 n
b0 m
b0 l
b100 k
b0 j
b1 i
b0 h
b100 g
b0 f
b0 e
b11111111111111100000100011 d
b0 c
0b
b100011 a
b1111100000100011 `
b11111111111111100000100011 _
0^
0]
0\
0[
0Z
0Y
0X
0W
b0 V
0U
b11111 T
b11111 S
b11111 R
0Q
0P
b0 O
0N
1M
0L
0K
0J
b0 I
1H
1G
0F
0E
0D
b0 C
b0 B
b0 A
b0 @
b1 ?
b0 >
b0 =
0<
b1 ;
b0 :
b100 9
08
07
b0 6
b0 5
14
b0 3
b11111 2
b11111 1
b11111 0
b0 /
b0 .
b0 -
b0 ,
b1111100000100011 +
b11111111111111100000100011 *
b1111100000100011 )
b11111111111111100000100011 (
1'
b11000000000100 &
b11000000000000 %
b11000000000100 $
b0 #
1"
0!
$end
#1000
b100000 z
b10000000000 o
1!
#2000
0!
#3000
b10000000000 o
b100000 z
1!
#4000
0!
#5000
b100000 z
b10000000000 o
1!
#6000
0!
#7000
b10000000000 o
b100000 z
1!
#8000
0!
#9000
b100000 z
b10000000000 o
1!
#10000
0!
0"
#11000
b11010011110010000000000000000 w
b11010011110010000000000000000 /
b11010011110010000000000000000 A
b11010011110010000000000000000 j
b1101001111001 =
b1 6
b1 f
1<
b101 ;
b101 ?
b101 i
b1101001111001 )
b1101001111001 q
b10 t
0M
b1001 #
b1001 >
b1001 O
b100001101001111001 *
b100001101001111001 _
b100001101001111001 #"
b1101001111001 +
b1101001111001 `
b1101001111001 p
b1101001111001 ""
b11 2
b11 T
b10 0
b10 R
b10 s
b0 1
b0 S
b0 r
b111001 a
1X
b1111 V
b111100000000100001101001111001 (
b111100000000100001101001111001 d
b111100000000100001101001111001 {
b11000000001000 &
b11000000001000 |
b11000000001000 &"
b11000000001000 $
b11000000001000 %"
b11000000000100 %
b11000000000100 n
b11000000000100 x
b11000000000100 }
b11000000000100 !"
b0 y
1!
#12000
0!
#13000
17
b11010100 /
b11010100 A
b11010100 j
b0 ;
b0 ?
b0 i
b0 w
b11010100 =
b11010100 )
b11010100 q
b1 5
b1 e
b0 9
b0 g
b0 k
0'
b11 #
b11 >
b11 O
b100000000011010100 *
b100000000011010100 _
b100000000011010100 #"
b11010100 +
b11010100 `
b11010100 p
b11010100 ""
b0 2
b0 T
b10100 a
0X
1W
b100011 V
b10001100000000100000000011010100 (
b10001100000000100000000011010100 d
b10001100000000100000000011010100 {
b11000000001100 &
b11000000001100 |
b11000000001100 &"
b11000000001100 $
b11000000001100 %"
b11000000001000 %
b11000000001000 n
b11000000001000 x
b11000000001000 }
b11000000001000 !"
1D
0H
b11010011110010000000000000000 ,
b11010011110010000000000000000 B
b11010011110010000000000000000 l
b11010011110010000000000000000 v
b11010011110010000000000000000 y
1!
#14000
0!
#15000
b1110101000 /
b1110101000 A
b1110101000 j
b1110101000 =
b1 t
1'
b1110101000 )
b1110101000 q
b1110 #
b1110 >
b1110 O
b10000001110101000 *
b10000001110101000 _
b10000001110101000 #"
b1110101000 +
b1110101000 `
b1110101000 p
b1110101000 ""
b1 0
b1 R
b1 s
b101000 a
b10001100000000010000001110101000 (
b10001100000000010000001110101000 d
b10001100000000010000001110101000 {
b11000000010000 &
b11000000010000 |
b11000000010000 &"
0D
1H
b0 ,
b0 B
b0 l
b0 v
b11000000010000 $
b11000000010000 %"
b11000000001100 %
b11000000001100 n
b11000000001100 x
b11000000001100 }
b11000000001100 !"
b0 y
1!
#16000
0!
#17000
b10 ;
b10 ?
b10 i
07
b101011110100010 w
b101011110100010 /
b101011110100010 A
b101011110100010 j
b101011110100010 =
b11111 t
b0 5
b0 e
b100 9
b100 g
b100 k
b101011110100010 )
b101011110100010 q
b11110 #
b11110 >
b11110 O
b1111110101011110100010 *
b1111110101011110100010 _
b1111110101011110100010 #"
b101011110100010 +
b101011110100010 `
b101011110100010 p
b101011110100010 ""
b1010 2
b1010 T
b11111 0
b11111 R
b11111 s
b1 1
b1 S
b1 r
b100010 a
1U
0W
b1101 V
b110100001111110101011110100010 (
b110100001111110101011110100010 d
b110100001111110101011110100010 {
b11000000010100 &
b11000000010100 |
b11000000010100 &"
b11000000010100 $
b11000000010100 %"
b11000000010000 %
b11000000010000 n
b11000000010000 x
b11000000010000 }
b11000000010000 !"
1!
#18000
0!
#19000
b101011110100010 w
b0 6
b0 f
b101011110100010 /
b101011110100010 A
b101011110100010 j
b0 =
0<
b0 ;
b0 ?
b0 i
b1000000100001 )
b1000000100001 q
b10 t
0'
1J
b0 #
b0 >
b0 O
b11111000110001000000100001 *
b11111000110001000000100001 _
b11111000110001000000100001 #"
b1000000100001 +
b1000000100001 `
b1000000100001 p
b1000000100001 ""
b10 2
b10 T
b11 0
b11 R
b11 s
0G
1F
b101011110100010 -
b101011110100010 @
b101011110100010 C
b101011110100010 u
b101011110100010 $"
b11111 1
b11111 S
b11111 r
b100001 a
0U
b0 V
b11111000110001000000100001 (
b11111000110001000000100001 d
b11111000110001000000100001 {
b11000000011000 &
b11000000011000 |
b11000000011000 &"
1D
0H
b0 ,
b0 B
b0 l
b0 v
b11000000011000 $
b11000000011000 %"
b11000000010100 %
b11000000010100 n
b11000000010100 x
b11000000010100 }
b11000000010100 !"
b101011110100010 y
1!
#20000
0!
#21000
b1111100000100001 )
b1111100000100001 q
b11111 t
b11111000001111100000100001 *
b11111000001111100000100001 _
b11111000001111100000100001 #"
b1111100000100001 +
b1111100000100001 `
b1111100000100001 p
b1111100000100001 ""
b11111 2
b11111 T
b0 0
b0 R
b0 s
b11111000001111100000100001 (
b11111000001111100000100001 d
b11111000001111100000100001 {
b11000000011100 &
b11000000011100 |
b11000000011100 &"
b11000000011100 $
b11000000011100 %"
b11000000011000 %
b11000000011000 n
b11000000011000 x
b11000000011000 }
b11000000011000 !"
1!
#22000
0!
#23000
b1 6
b1 f
1'
b0 w
1<
b0 )
b0 q
b0 t
b0 /
b0 A
b0 j
0J
b0 *
b0 _
b0 #"
b0 +
b0 `
b0 p
b0 ""
b0 2
b0 T
1G
0F
0D
1H
b0 -
b0 @
b0 C
b0 u
b0 $"
b0 1
b0 S
b0 r
b0 a
b0 (
b0 d
b0 {
b11000000100000 &
b11000000100000 |
b11000000100000 &"
b11000000100000 $
b11000000100000 %"
b11000000011100 %
b11000000011100 n
b11000000011100 x
b11000000011100 }
b11000000011100 !"
1!
#24000
0!
#25000
17
b100011111100 /
b100011111100 A
b100011111100 j
b100011111100 =
b100011111100 )
b100011111100 q
b1 t
b1 5
b1 e
b0 9
b0 g
b0 k
b11 #
b11 >
b11 O
b10000100011111100 *
b10000100011111100 _
b10000100011111100 #"
b100011111100 +
b100011111100 `
b100011111100 p
b100011111100 ""
b1 2
b1 T
b1 0
b1 R
b1 s
b111100 a
1W
b100011 V
b10001100000000010000100011111100 (
b10001100000000010000100011111100 d
b10001100000000010000100011111100 {
b11000000100100 &
b11000000100100 |
b11000000100100 &"
b11000000100100 $
b11000000100100 %"
b11000000100000 %
b11000000100000 n
b11000000100000 x
b11000000100000 }
b11000000100000 !"
b0 y
1!
#26000
0!
#27000
b1 ;
b1 ?
b1 i
07
b0 6
b0 f
b101011110100010 w
0'
0<
b0 =
b0 5
b0 e
b100 9
b100 g
b100 k
b100000100011 )
b100000100011 q
b101011110100010 /
b101011110100010 A
b101011110100010 j
1M
b0 #
b0 >
b0 O
b11111000010000100000100011 *
b11111000010000100000100011 _
b11111000010000100000100011 #"
b100000100011 +
b100000100011 `
b100000100011 p
b100000100011 ""
0G
1F
1D
0H
b101011110100010 -
b101011110100010 @
b101011110100010 C
b101011110100010 u
b101011110100010 $"
b11111 1
b11111 S
b11111 r
b100011 a
0W
b0 V
b11111000010000100000100011 (
b11111000010000100000100011 d
b11111000010000100000100011 {
b11000000101000 &
b11000000101000 |
b11000000101000 &"
b11000000101000 $
b11000000101000 %"
b11000000100100 %
b11000000100100 n
b11000000100100 x
b11000000100100 }
b11000000100100 !"
1!
#28000
0!
#29000
b1 6
b1 f
1<
b10 ;
b10 ?
b10 i
b1000001000110101 )
b1000001000110101 q
b0 t
b1101011110110111 w
0M
0'
b1000 #
b1000 >
b1000 O
b10000001000001000110101 *
b10000001000001000110101 _
b10000001000001000110101 #"
b1000001000110101 +
b1000001000110101 `
b1000001000110101 p
b1000001000110101 ""
b10000 2
b10000 T
b0 0
b0 R
b0 s
b10 1
b10 S
b10 r
b110101 a
1U
b1101 V
b1101011110110111 /
b1101011110110111 A
b1101011110110111 j
b110100010000001000001000110101 (
b110100010000001000001000110101 d
b110100010000001000001000110101 {
b11000000101100 &
b11000000101100 |
b11000000101100 &"
b1000001000110101 =
b11000000101100 $
b11000000101100 %"
b11000000101000 %
b11000000101000 n
b11000000101000 x
b11000000101000 }
b11000000101000 !"
1D
0H
b0 ,
b0 B
b0 l
b0 v
b101011110100010 y
1!
#30000
0!
#31000
b0 6
b0 f
b101011110100010 =
b11111111111111111010100001011110 w
0<
b1 ;
b1 ?
b1 i
b1000000100011 )
b1000000100011 q
b10 t
b11111111111111111010100001011110 /
b11111111111111111010100001011110 A
b11111111111111111010100001011110 j
1M
b0 #
b0 >
b0 O
b111110001000000100011 *
b111110001000000100011 _
b111110001000000100011 #"
b1000000100011 +
b1000000100011 `
b1000000100011 p
b1000000100011 ""
b10 2
b10 T
b101011110100010 ,
b101011110100010 B
b101011110100010 l
b101011110100010 v
b11111 0
b11111 R
b11111 s
1G
0F
1D
0H
b0 -
b0 @
b0 C
b0 u
b0 $"
b0 1
b0 S
b0 r
b100011 a
0U
b0 V
b111110001000000100011 (
b111110001000000100011 d
b111110001000000100011 {
b11000000110000 &
b11000000110000 |
b11000000110000 &"
b11000000110000 $
b11000000110000 %"
b11000000101100 %
b11000000101100 n
b11000000101100 x
b11000000101100 }
b11000000101100 !"
b0 y
1!
#32000
0!
