P4/P4Judger/std/def.v
`ifndef def
`define def

	//IFU
	`define b 3'd1
	`define j 3'd2
	`define jr 3'd3
	`define origin 32'h3000
	`define code_addr 3072
	`define delay 32'd4
	//GRF
	`define ra 6'd31
	`define pce 6'd32
	`define ext 6'd33
	`define extu 6'd34
	`define uext 6'd35
	`define shmt 6'd36
	`define inst 6'd37
	//ALU
	`define add 6'd1
	`define sub 6'd2
	`define addu 6'd3
	`define subu 6'd4
	`define and 6'd5
	`define or 6'd6
	`define xor 6'd7
	`define nor 6'd8
	`define sll 6'd9
	`define srl 6'd10
	`define sra 6'd11
	//DM
	`define wd 3'd1
	`define hf 3'd2
	`define bt 3'd3
	`define uhf 3'd4
	`define ubt 3'd5
	//CMP
	`define eql 1'b0
	`define ltz 1'b1
	//CTRL
	`define zero 6'b0
	`define ifup 6

`endif

P4/P4Judger/std/pm.v
`include "def.v"
module pm(input wire[32*7-1:0]I,output wire[32*6-1:0]O,
		  output wire[32*3-1:0]Instr,output wire[32*3-1:0]PC,
		  input wire[12:0]opI,output wire[13:0]opO,output wire[1:0]b,
		  input wire clk,rst);
	
	wire[31:0]instr;wire[31:0]pc;
	wire[31:0]rfz;wire[31:0]rfw;wire[31:0]rfm;
	wire[31:0]aluz;wire[31:0]dmz;

	assign {instr,pc,rfz,rfw,rfm,aluz,dmz}=I;
	assign {b[`eql],b[`ltz]} = {rfw==rfm,rfw[31]};

	wire[2:0]ifup;wire[5:0]alup;wire[2:0]dmp;wire dme;wire[2:0]wb;
	assign {ifup,alup,dmp,dme} = opI;
	
	wire[31:0]alux;wire[31:0]aluy;wire[31:0]ifum;
	wire[31:0]cmpx;wire[31:0]cmpy;
	wire[31:0]dmax;wire[31:0]dmx; wire[31:0]rfx;

	assign {ifum,alux,aluy,dmx, dmax,rfx}
		 = {rfz, rfz, rfw, rfm, aluz,alup&&(!dmp)?aluz:dmz};
	assign O = {ifum,alux,aluy,dmax,dmx,rfx};
	assign Instr = {instr,instr,instr};
	assign PC = {pc,pc,pc};
	assign opO = {1'b1,opI};

endmodule

P4/P4Judger/std/dm.v
`include "def.v"
module dm(input wire[31:0]ax,input wire[31:0]x,output wire[31:0]z,
		  input wire[31:0]pcw,input wire[2:0]op,input wire clk,rst,en);
	
	reg [31:0]ram[0:4095];
	wire[29:0]i;wire[4:0]j;reg[31:0]wri;
	
	assign {i,j}={ax&32'd4095,3'b0};
	always@(*)begin
		wri=ram[i];
		case(op)
			`wd:wri=x;
			`hf:wri[j+:16]=x[15:0];
			`bt:wri[j+: 8]=x[ 7:0];
		endcase
	end
	
	integer p; initial for(p=0;p<4096;p=p+1)ram[p]<=0;
	always@(posedge clk)begin
		if(rst)for(p=0;p<4096;p=p+1)ram[p]=0;
		else if(en)begin
			ram[i]<=wri;
			$display("@%h: *%h <= %h",pcw, {i,2'b0}, wri);//$display("%0d@%h: *%h <= %h",$time, pcw, {i,2'b0}, wri);
		end
	end

	assign z=	(op == `wd)? ram[i]:
				(op == `hf)? {{16{ram[i][j+15]}},ram[i][j+:16]}:
				(op == `bt)? {{24{ram[i][j+ 7]}},ram[i][j+: 8]}:
				(op ==`uhf)? {16'b0,ram[i][j+:16]}:
				(op ==`ubt)? {24'b0,ram[i][j+: 8]}:
				x;
endmodule

P4/P4Judger/std/alu.v
`include "def.v"
module alu(input wire[31:0]x,input wire[31:0]y,output wire[31:0]z,
		   input wire[5:0]op);
	reg[32:0]zz;
	
	always@(*)case(op)
		`add:zz<={x[31],x}+{y[31],y};
		`sub:zz<={x[31],x}-{y[31],y};
		`addu:zz<={1'b0,x}+{1'b0,y};
		`subu:zz<={1'b0,x}-{1'b0,y};
		`or:zz<={1'b0,x|y};
		`sll:zz<=(x<<y[4:0]);
		`srl:zz<=(x>>y[4:0]);
		`sra:zz<=$signed(x)>>>y[4:0];
	endcase
	
	assign z=zz[31:0];

endmodule

P4/P4Judger/std/ctrl.v
`include "def.v"
module ctrl(input wire[31:0]instr,output wire[12:0]ops,input wire[1:0]b,
			output reg[5:0]az,output reg[5:0]aw,output reg[5:0]am,output reg[5:0]ax);
	
	wire[5:0]code;wire[5:0]func;wire[4:0]shamt;
	wire[5:0]rs;wire[5:0]rt;wire[5:0]rd;

	assign {code,rs[4:0],rt[4:0],rd[4:0],shamt,func}=instr;
	assign {rs[5],rt[5],rd[5]}=3'b0;

	reg[2:0]ifup;reg[5:0]alup;reg[2:0]dmp;reg dme;
	assign ops={ifup,alup,dmp,dme};

	always@(*)case(code)
		6'b0: case(func)
			6'b100001:begin {az,aw,am,ax}<={rs,rt,6'b0,rd};
			/*addu*/		{ifup,alup,dmp,dme}<={3'b0,`addu,3'b0,1'b0}; end
			6'b100011:begin {az,aw,am,ax}<={rs,rt,6'b0,rd};
			/*subu*/		{ifup,alup,dmp,dme}<={3'b0,`subu,3'b0,1'b0}; end
			6'b001000:begin {az,aw,am,ax}<={rs,6'b0,6'b0,6'b0};
			/* jr */		{ifup,alup,dmp,dme}<={`jr,6'b0,3'b0,1'b0};   end
			6'b001001:begin {az,aw,am,ax}<={rs,6'b0,`pce,rd};
			/*jalr*/		{ifup,alup,dmp,dme}<={`jr,6'b0,3'b0,1'b0};   end
			6'b000000:begin {az,aw,am,ax}<={rt,`shmt,6'b0,rd};
			/*sll */		{ifup,alup,dmp,dme}<={3'b0,`sll,3'b0,1'b0};  end
			default:  begin {az,aw,am,ax}<={6'b0,6'b0,6'b0,6'b0};
			/*xxxx*/		{ifup,alup,dmp,dme}<={3'b0,6'b0,3'b0,1'b0};  end
		endcase
		6'b000010:begin {az,aw,am,ax}<={`inst,6'b0,6'b0,6'b0};
		/* j  */		{ifup,alup,dmp,dme}<={`j,6'b0,3'b0,1'b0};   	 end
		6'b000011:begin {az,aw,am,ax}<={`inst,6'b0,`pce,`ra};
		/*jal */		{ifup,alup,dmp,dme}<={`j,6'b0,3'b0,1'b0};   	 end
		6'b000100:begin {az,aw,am,ax}<={`inst,rs,rt,6'b0};
		/*beq */		{ifup,alup,dmp,dme}<={(b[`eql])?`b:3'b0,6'b0,3'b0,1'b0}; end
		6'b001000:begin {az,aw,am,ax}<={rs,`ext,6'b0,rt};
		/*addi*/		{ifup,alup,dmp,dme}<={3'b0,`add,3'b0,1'b0};		 end
		6'b001101:begin {az,aw,am,ax}<={rs,`extu,6'b0,rt};
		/*ori */		{ifup,alup,dmp,dme}<={3'b0,`or,3'b0,1'b0};		 end
		6'b001111:begin {az,aw,am,ax}<={6'b0,`uext,6'b0,rt};
		/*lui */		{ifup,alup,dmp,dme}<={3'b0,`or,3'b0,1'b0};		 end
		6'b100011:begin {az,aw,am,ax}<={rs,`ext,6'b0,rt};
		/* lw */		{ifup,alup,dmp,dme}<={3'b0,`add,`wd,1'b0};		 end
		6'b101011:begin {az,aw,am,ax}<={rs,`ext,rt,6'b0};
		/* sw */		{ifup,alup,dmp,dme}<={3'b0,`add,`wd,1'b1};		 end
		default:  begin {az,aw,am,ax}<={6'b0,6'b0,6'b0,6'b0};
		/*xxxx*/		{ifup,alup,dmp,dme}<={3'b0,6'b0,3'b0,1'b0};		 end
	endcase

endmodule

P4/P4Judger/std/grf.v
`include "def.v"
module grf(input  wire[5:0]az,input  wire[5:0]aw,input  wire[5:0]am,input wire[5:0]ax,
		   output wire[31:0]z,output wire[31:0]w,output wire[31:0]m,input wire[31:0]x,
		   input wire [31:0]instr,input wire [31:0]pc,input wire [31:0]pcw,
		   input wire clk, rst);
	
	reg[31:0]rf[0:37];
	wire[31:0]wri;wire[5:0]wrp;
	assign wri = x;
	assign wrp = ax;

	always@(*)begin
		rf[`pce] <= pc+31'd4;
		rf[`ext] <= {{16{instr[15]}},instr[15:0]};
		rf[`extu]<= {16'b0,instr[15:0]};
		rf[`uext]<= {instr[15:0],16'b0};
		rf[`shmt]<= instr[10:6];
		rf[`inst]<= instr;
	end

	integer i; initial for(i=0;i<32;i=i+1)rf[i]<=0;
	always@(posedge clk)begin
		if(rst)for(i=0;i<32;i=i+1)rf[i]<=0;
		else if(wrp[4:0]!=5'b0)begin
			rf[wrp[4:0]]<=wri;
			$display("@%h: $%d <= %h",pcw, wrp, wri);//$display("%0d@%h: $%d <= %h",$time, pcw, wrp, wri);
		end
		rf[0]<=32'b0;
	end

	assign z = rf[az];
	assign w = rf[aw];
	assign m = rf[am];

endmodule

P4/P4Judger/std/ifu.v
`include "def.v"
module ifu(input wire[31:0]imm,input wire[2:0]op,input clk,rst,en,
		   output reg[31:0]pc,output wire[31:0]instr);
	
	reg[31:0]rom[`code_addr:`code_addr+4095];
	wire [31:0]npc;wire[31:0]opc;
	
	assign opc=pc-`delay;
	assign npc=(op==0 ) ?pc+32'd4:
			   (op==`b) ?pc+`delay+{{14{imm[15]}},imm[15:0],2'b0}:
			   (op==`j) ?{opc[31:28],imm[25:0],2'b0}:
			   (op==`jr)?imm:pc+32'd4;
	
	initial begin pc=`origin; $readmemh("code.txt",rom); end
	// initial $readmemh("code_handler.txt", rom, `code_addr+1120, `code_addr+2047);
	always @(posedge clk)begin
		if (rst)pc<=`origin;
		else if (en)pc<=npc;
		else pc<=pc;
	end
	
	assign instr=rom[pc[31:2]];

endmodule

P4/P4Judger/std/mips.v
`include "def.v"
`include "alu.v"
`include "ctrl.v"
`include "dm.v"
`include "grf.v"
`include "ifu.v"
`include "pm.v"
module mips(input clk,reset);
	
	wire[31:0]instrp;wire[31:0]instr[0:3]; wire[31:0]pcp;wire[31:0]pc[0:3];
	
	wire[31:0]ifum;wire[2:0]ifup;wire ifue;
	ifu IFU(.imm(ifum),.op(ifup),.clk(clk),.rst(reset),
			.instr(instrp),.pc(pcp),.en(ifue));

	wire[5:0]az;wire[5:0]aw;wire[5:0]am;wire[5:0]ax;
	wire[31:0]z;wire[31:0]w;wire[31:0]m;wire[31:0]x;
	
	wire[1:0]cmpb;wire[12:0]ops;

	grf  GRF( .z(z),.w(w),.m(m),.x(x), .pcw(pc[3]),.clk(clk),.rst(reset),
			  .az(az),.aw(aw),.am(am),.ax(ax),.instr(instr[0]),.pc(pc[0]));
	ctrl CTRL(.az(az),.aw(aw),.am(am),.ax(ax),.instr(instr[0]),.ops(ops),.b(cmpb));

	wire[31:0]alux;wire[31:0]aluy;wire[31:0]aluz;wire[5:0]alup;
	alu ALU(.x(alux),.y(aluy),.z(aluz),.op(alup));

	wire[31:0]dmax;wire[31:0]dmx;wire[31:0]dmz;
	wire[2:0]dmp;wire dme;
	dm  DM (.ax(dmax),.x(dmx),.z(dmz),.pcw(pc[2]),
			.op(dmp),.en(dme),.clk(clk),.rst(reset));

	pm  PM (.I({instrp,pcp,z,w,m,aluz,dmz}),.O({ifum,alux,aluy,dmax,dmx,x}),
			.Instr({instr[0],instr[2],instr[3]}),.PC({pc[0],pc[2],pc[3]}),
			.opI(ops),.opO({ifue,ifup,alup,dmp,dme}),.b(cmpb));

endmodule

P4/P4Judger/std/mips_tb.v
`timescale 1ns / 1ps
`include "mips.v"

////////////////////////////////////////////////////////////////////////////////
// Company: Beihang University
// Engineer: FlyChy
//
// Create Date:   19:25:35 11/12/2021
// Design Name:   mips
// Module Name:   G:/MyWorkspace/Computer_Organization/P4/P4_L0_CPU/mips_tb.v
// Project Name:  P4_L0_CPU
// Tool versions:  ISE 14.7
// Description: 
//
// Verilog Test Fixture created by ISE for module: mips
//
// Dependencies: 
// 
// Revision:
// Revision 0.01 - File Created
// Additional Comments:
// 
////////////////////////////////////////////////////////////////////////////////

module mips_tb;

	// Inputs
	reg clk;
	reg reset;

	// Instantiate the Unit Under Test (UUT)
	mips uut (
		.clk(clk), 
		.reset(reset)
	);

	always #1 clk = ~clk;

	initial begin
		$dumpfile("mips_tb.vcd");
		$dumpvars;
		// Initialize Inputs
		clk = 0;
		reset = 1;

		#10;
		reset = 0;
        #4096;
		$finish;
		// Add stimulus here

	end
      
endmodule

P4/P4Judger/std/mips_tb.vcd
$date
	Wed Nov 17 17:19:06 2021
$end
$version
	Icarus Verilog
$end
$timescale
	1ps
$end
$scope module mips_tb $end
$var reg 1 ! clk $end
$var reg 1 " reset $end
$scope module uut $end
$var wire 1 ! clk $end
$var wire 1 " reset $end
$var wire 32 # z [31:0] $end
$var wire 32 $ x [31:0] $end
$var wire 32 % w [31:0] $end
$var wire 32 & pcp [31:0] $end
$var wire 13 ' ops [12:0] $end
$var wire 32 ( m [31:0] $end
$var wire 32 ) instrp [31:0] $end
$var wire 3 * ifup [2:0] $end
$var wire 32 + ifum [31:0] $end
$var wire 1 , ifue $end
$var wire 32 - dmz [31:0] $end
$var wire 32 . dmx [31:0] $end
$var wire 3 / dmp [2:0] $end
$var wire 1 0 dme $end
$var wire 32 1 dmax [31:0] $end
$var wire 2 2 cmpb [1:0] $end
$var wire 6 3 az [5:0] $end
$var wire 6 4 ax [5:0] $end
$var wire 6 5 aw [5:0] $end
$var wire 6 6 am [5:0] $end
$var wire 32 7 aluz [31:0] $end
$var wire 32 8 aluy [31:0] $end
$var wire 32 9 alux [31:0] $end
$var wire 6 : alup [5:0] $end
$scope module ALU $end
$var wire 6 ; op [5:0] $end
$var wire 32 < x [31:0] $end
$var wire 32 = y [31:0] $end
$var wire 32 > z [31:0] $end
$var reg 33 ? zz [32:0] $end
$upscope $end
$scope module CTRL $end
$var wire 32 @ instr [31:0] $end
$var wire 5 A shamt [4:0] $end
$var wire 6 B rt [5:0] $end
$var wire 6 C rs [5:0] $end
$var wire 6 D rd [5:0] $end
$var wire 13 E ops [12:0] $end
$var wire 6 F func [5:0] $end
$var wire 6 G code [5:0] $end
$var wire 2 H b [1:0] $end
$var reg 6 I alup [5:0] $end
$var reg 6 J am [5:0] $end
$var reg 6 K aw [5:0] $end
$var reg 6 L ax [5:0] $end
$var reg 6 M az [5:0] $end
$var reg 1 N dme $end
$var reg 3 O dmp [2:0] $end
$var reg 3 P ifup [2:0] $end
$upscope $end
$scope module DM $end
$var wire 32 Q ax [31:0] $end
$var wire 1 ! clk $end
$var wire 1 0 en $end
$var wire 3 R op [2:0] $end
$var wire 32 S pcw [31:0] $end
$var wire 1 " rst $end
$var wire 32 T x [31:0] $end
$var wire 32 U z [31:0] $end
$var wire 5 V j [4:0] $end
$var wire 30 W i [29:0] $end
$var reg 32 X wri [31:0] $end
$var integer 32 Y p [31:0] $end
$upscope $end
$scope module GRF $end
$var wire 6 Z am [5:0] $end
$var wire 6 [ aw [5:0] $end
$var wire 6 \ ax [5:0] $end
$var wire 6 ] az [5:0] $end
$var wire 1 ! clk $end
$var wire 32 ^ instr [31:0] $end
$var wire 32 _ m [31:0] $end
$var wire 32 ` pc [31:0] $end
$var wire 32 a pcw [31:0] $end
$var wire 1 " rst $end
$var wire 32 b w [31:0] $end
$var wire 32 c wri [31:0] $end
$var wire 6 d wrp [5:0] $end
$var wire 32 e x [31:0] $end
$var wire 32 f z [31:0] $end
$var integer 32 g i [31:0] $end
$upscope $end
$scope module IFU $end
$var wire 1 ! clk $end
$var wire 1 , en $end
$var wire 32 h imm [31:0] $end
$var wire 32 i instr [31:0] $end
$var wire 3 j op [2:0] $end
$var wire 1 " rst $end
$var wire 32 k opc [31:0] $end
$var wire 32 l npc [31:0] $end
$var reg 32 m pc [31:0] $end
$upscope $end
$scope module PM $end
$var wire 224 n I [223:0] $end
$var wire 1 o clk $end
$var wire 13 p opI [12:0] $end
$var wire 1 q rst $end
$var wire 32 r rfz [31:0] $end
$var wire 32 s rfx [31:0] $end
$var wire 32 t rfw [31:0] $end
$var wire 32 u rfm [31:0] $end
$var wire 32 v pc [31:0] $end
$var wire 14 w opO [13:0] $end
$var wire 32 x instr [31:0] $end
$var wire 3 y ifup [2:0] $end
$var wire 32 z ifum [31:0] $end
$var wire 32 { dmz [31:0] $end
$var wire 32 | dmx [31:0] $end
$var wire 3 } dmp [2:0] $end
$var wire 1 ~ dme $end
$var wire 32 !" dmax [31:0] $end
$var wire 2 "" b [1:0] $end
$var wire 32 #" aluz [31:0] $end
$var wire 32 $" aluy [31:0] $end
$var wire 32 %" alux [31:0] $end
$var wire 6 &" alup [5:0] $end
$var wire 96 '" PC [95:0] $end
$var wire 192 (" O [191:0] $end
$var wire 96 )" Instr [95:0] $end
$upscope $end
$upscope $end
$upscope $end
$enddefinitions $end
#0
$dumpvars
b111111111111111000001000110000001111111111111110000010001100000011111111111111100000100011 )"
b0 ("
b110000000000000000000000000000001100000000000000000000000000000011000000000000 '"
b100 &"
b0 %"
b0 $"
b0 #"
b1 ""
b0 !"
0~
b0 }
b0 |
b0 {
b0 z
b0 y
b11111111111111100000100011 x
b10000001000000 w
b11000000000000 v
b0 u
b0 t
b0 s
b0 r
zq
b1000000 p
zo
b11111111111111100000100011000000000000000000110000000000000000000000000000000000000000000000000000000000000000000000000000000000000000000000000000000000000000000000000000000000000000000000000000000000000000000000000000 n
b11000000000000 m
b11000000000100 l
b10111111111100 k
b0 j
b11111111111111100000100011 i
b0 h
b100000 g
b0 f
b0 e
b11111 d
b0 c
b0 b
b11000000000000 a
b11000000000000 `
b0 _
b11111111111111100000100011 ^
b11111 ]
b11111 \
b11111 [
b0 Z
b1000000000000 Y
b0 X
b0 W
b0 V
b0 U
b0 T
b11000000000000 S
b0 R
b0 Q
b0 P
b0 O
0N
b11111 M
b11111 L
b11111 K
b0 J
b100 I
b1 H
b0 G
b100011 F
b1000000 E
b11111 D
b11111 C
b11111 B
b0 A
b11111111111111100000100011 @
b0 ?
b0 >
b0 =
b0 <
b100 ;
b100 :
b0 9
b0 8
b0 7
b0 6
b11111 5
b11111 4
b11111 3
b1 2
b0 1
00
b0 /
b0 .
b0 -
1,
b0 +
b0 *
b11111111111111100000100011 )
b0 (
b1000000 '
b11000000000000 &
b0 %
b0 $
b0 #
1"
0!
$end
#1000
b100000 g
b1000000000000 Y
1!
#2000
0!
#3000
b1000000000000 Y
b100000 g
1!
#4000
0!
#5000
b100000 g
b1000000000000 Y
1!
#6000
0!
#7000
b1000000000000 Y
b100000 g
1!
#8000
0!
#9000
b100000 g
b1000000000000 Y
1!
#10000
0!
0"
#11000
b11010011110010000000000000000 c
b11010011110010000000000000000 $
b11010011110010000000000000000 e
b11010011110010000000000000000 s
b11010011110010000000000000000 1
b11010011110010000000000000000 Q
b11010011110010000000000000000 !"
b11010011110010000000000000000 #"
b11010011110010000000000000000 7
b11010011110010000000000000000 >
b11010011110010000000000000000 ?
b11010011110010000000000000000 8
b11010011110010000000000000000 =
b0 2
b0 H
b0 ""
b11010011110010000000000000000000110100111100100000000000000000000000000000000000000000000000000011010011110010000000000000000 ("
b11010011110010000000000000000 $"
b110 &"
b110 :
b110 ;
b11010011110010000000000000000 t
b10000001100000 w
b1100000 '
b1100000 E
b1100000 p
b110 I
b0 3
b0 M
b0 ]
b11010011110010000000000000000 %
b11010011110010000000000000000 b
b100011 5
b100011 K
b100011 [
b10 d
b10 4
b10 L
b10 \
b1111 G
b0 C
b10 B
b11 D
b1001 A
b111001 F
b111100000000100001101001111001 @
b111100000000100001101001111001 ^
b1111000000001000011010011110010011110000000010000110100111100100111100000000100001101001111001 )"
b111100000000100001101001111001 x
b11000000000100 a
b11000000000100 S
b11000000000100 `
b11000000001000 l
b111100000000100001101001111001 )
b111100000000100001101001111001 i
b110000000001000000000000000000001100000000010000000000000000000011000000000100 '"
b11000000000100 v
b11000000000000 k
b111100000000100001101001111001000000000000000000110000000001000000000000000000000000000000000000011010011110010000000000000000000000000000000000000000000000000001101001111001000000000000000000000000000000000000000000000000 n
b11000000000100 &
b11000000000100 m
1!
#12000
0!
#13000
b110101 W
b11010100 1
b11010100 Q
b11010100 !"
b11010100 #"
b11010100 7
b11010100 >
b11010100 ?
b0 c
b0 $
b0 e
b0 s
b11010100 8
b11010100 =
b11010100000000000000000000000000110101000000000000000000000000000000000000000000000000000000000000000000 ("
b11010100 $"
b1 &"
b1 :
b1 ;
b1 }
b1 /
b1 R
b11010100 t
b1 I
b10000000010010 w
b10010 '
b10010 E
b10010 p
b1 O
b100001 5
b100001 K
b100001 [
b11010100 %
b11010100 b
b100011 G
b0 D
b11 A
b10100 F
b10001100000000100000000011010100 @
b10001100000000100000000011010100 ^
b100011000000001000000000110101001000110000000010000000001101010010001100000000100000000011010100 )"
b10001100000000100000000011010100 x
b11000000001000 a
b11000000001000 S
b11000000001000 `
b11000000001100 l
b10001100000000100000000011010100 )
b10001100000000100000000011010100 i
b110000000010000000000000000000001100000000100000000000000000000011000000001000 '"
b11000000001000 v
b11000000000100 k
b10001100000000100000000011010100000000000000000000110000000010000000000000000000000000000000000000000000000000000000000011010100000000000000000000000000000000000000000000000000000000001101010000000000000000000000000000000000 n
b11000000001000 &
b11000000001000 m
1!
#14000
0!
#15000
b11101010 W
b1110101000 1
b1110101000 Q
b1110101000 !"
b1110101000 #"
b1110101000 7
b1110101000 >
b1110101000 ?
b1110101000 8
b1110101000 =
b1110101000000000000000000000000011101010000000000000000000000000000000000000000000000000000000000000000000 ("
b1110101000 $"
b1110101000 t
b1 d
b1 4
b1 L
b1 \
b1110101000 %
b1110101000 b
b1 B
b1110 A
b101000 F
b10001100000000010000001110101000 @
b10001100000000010000001110101000 ^
b100011000000000100000011101010001000110000000001000000111010100010001100000000010000001110101000 )"
b10001100000000010000001110101000 x
b11000000001100 a
b11000000001100 S
b11000000001100 `
b11000000010000 l
b10001100000000010000001110101000 )
b10001100000000010000001110101000 i
b110000000011000000000000000000001100000000110000000000000000000011000000001100 '"
b11000000001100 v
b11000000001000 k
b10001100000000010000001110101000000000000000000000110000000011000000000000000000000000000000000000000000000000000000001110101000000000000000000000000000000000000000000000000000000000111010100000000000000000000000000000000000 n
b11000000001100 &
b11000000001100 m
1!
#16000
0!
#17000
b10000 V
b111101000 W
b101011110100010 1
b101011110100010 Q
b101011110100010 !"
b101011110100010 #"
b101011110100010 7
b101011110100010 >
b101011110100010 ?
b101011110100010 c
b101011110100010 $
b101011110100010 e
b101011110100010 s
b101011110100010 8
b101011110100010 =
b101011110100010000000000000000001010111101000100000000000000000000000000000000000000000000000000101011110100010 ("
b101011110100010 $"
b110 &"
b110 :
b110 ;
b0 }
b0 /
b0 R
b101011110100010 t
b110 I
b10000001100000 w
b1100000 '
b1100000 E
b1100000 p
b0 O
b1 3
b1 M
b1 ]
b100010 5
b100010 K
b100010 [
b11111 d
b11111 4
b11111 L
b11111 \
b101011110100010 %
b101011110100010 b
b1101 G
b1 C
b11111 B
b1010 D
b11110 A
b100010 F
b110100001111110101011110100010 @
b110100001111110101011110100010 ^
b1101000011111101010111101000100011010000111111010101111010001000110100001111110101011110100010 )"
b110100001111110101011110100010 x
b11000000010000 a
b11000000010000 S
b11000000010000 `
b11000000010100 l
b110100001111110101011110100010 )
b110100001111110101011110100010 i
b110000000100000000000000000000001100000001000000000000000000000011000000010000 '"
b11000000010000 v
b11000000001100 k
b110100001111110101011110100010000000000000000000110000000100000000000000000000000000000000000000000000000000000101011110100010000000000000000000000000000000000000000000000000010101111010001000000000000000000000000000000000 n
b11000000010000 &
b11000000010000 m
1!
#18000
0!
#19000
b101011110100010 9
b101011110100010 <
b101011110100010 +
b101011110100010 h
b0 8
b0 =
b101011110100010 %"
b101011110100010 z
b1 2
b1 H
b1 ""
b1010111101000100000000000000000010101111010001000000000000000000000000000000000000000000000000001010111101000100000000000000000000000000000000000000000000000000101011110100010 ("
b0 $"
b11 &"
b11 :
b11 ;
b101011110100010 r
b0 t
b10000000110000 w
b110000 '
b110000 E
b110000 p
b11 I
b101011110100010 #
b101011110100010 f
b11111 3
b11111 M
b11111 ]
b11 5
b11 K
b11 [
b10 d
b10 4
b10 L
b10 \
b0 %
b0 b
b0 G
b11111 C
b11 B
b10 D
b0 A
b100001 F
b11111000110001000000100001 @
b11111000110001000000100001 ^
b111110001100010000001000010000001111100011000100000010000100000011111000110001000000100001 )"
b11111000110001000000100001 x
b11000000010100 a
b11000000010100 S
b11000000010100 `
b11000000011000 l
b11111000110001000000100001 )
b11111000110001000000100001 i
b110000000101000000000000000000001100000001010000000000000000000011000000010100 '"
b11000000010100 v
b11000000010000 k
b11111000110001000000100001000000000000000000110000000101000000000000000000010101111010001000000000000000000000000000000000000000000000000000000000000000000000000000000000010101111010001000000000000000000000000000000000 n
b11000000010100 &
b11000000010100 m
1!
#20000
0!
#21000
b0 5
b0 K
b0 [
b11111 d
b11111 4
b11111 L
b11111 \
b0 B
b11111 D
b11111000001111100000100001 @
b11111000001111100000100001 ^
b111110000011111000001000010000001111100000111110000010000100000011111000001111100000100001 )"
b11111000001111100000100001 x
b11000000011000 a
b11000000011000 S
b11000000011000 `
b11000000011100 l
b11111000001111100000100001 )
b11111000001111100000100001 i
b110000000110000000000000000000001100000001100000000000000000000011000000011000 '"
b11000000011000 v
b11000000010100 k
b11111000001111100000100001000000000000000000110000000110000000000000000000010101111010001000000000000000000000000000000000000000000000000000000000000000000000000000000000010101111010001000000000000000000000000000000000 n
b11000000011000 &
b11000000011000 m
1!
#22000
0!
#23000
b0 V
b0 W
b0 c
b0 $
b0 e
b0 s
b0 1
b0 Q
b0 !"
b0 #"
b0 7
b0 >
b0 ?
b0 9
b0 <
b0 +
b0 h
b0 %"
b0 ("
b0 z
b1001 &"
b1001 :
b1001 ;
b0 r
b10000010010000 w
b10010000 '
b10010000 E
b10010000 p
b1001 I
b0 #
b0 f
b0 3
b0 M
b0 ]
b100100 5
b100100 K
b100100 [
b0 d
b0 4
b0 L
b0 \
b0 C
b0 D
b0 F
b0 @
b0 ^
b0 )"
b0 x
b11000000011100 a
b11000000011100 S
b11000000011100 `
b11000000100000 l
b0 )
b0 i
b110000000111000000000000000000001100000001110000000000000000000011000000011100 '"
b11000000011100 v
b11000000011000 k
b110000000111000000000000000000000000000000000000000000000000000000000000000000000000000000000000000000000000000000000000000000000000000000000000000000000000000000000000000000 n
b11000000011100 &
b11000000011100 m
1!
#24000
0!
#25000
b1000111111 W
b100011111100 1
b100011111100 Q
b100011111100 !"
b100011111100 #"
b100011111100 7
b100011111100 >
b100011111100 ?
b100011111100 8
b100011111100 =
b0 2
b0 H
b0 ""
b100011111100000000000000000000001000111111000000000000000000000000000000000000000000000000000000000000000000 ("
b100011111100 $"
b1 &"
b1 :
b1 ;
b1 }
b1 /
b1 R
b100011111100 t
b1 I
b10000000010010 w
b10010 '
b10010 E
b10010 p
b1 O
b100001 5
b100001 K
b100001 [
b1 d
b1 4
b1 L
b1 \
b100011111100 %
b100011111100 b
b100011 G
b1 B
b1 D
b11 A
b111100 F
b10001100000000010000100011111100 @
b10001100000000010000100011111100 ^
b100011000000000100001000111111001000110000000001000010001111110010001100000000010000100011111100 )"
b10001100000000010000100011111100 x
b11000000100000 a
b11000000100000 S
b11000000100000 `
b11000000100100 l
b10001100000000010000100011111100 )
b10001100000000010000100011111100 i
b110000001000000000000000000000001100000010000000000000000000000011000000100000 '"
b11000000100000 v
b11000000011100 k
b10001100000000010000100011111100000000000000000000110000001000000000000000000000000000000000000000000000000000000000100011111100000000000000000000000000000000000000000000000000000010001111110000000000000000000000000000000000 n
b11000000100000 &
b11000000100000 m
1!
#26000
0!
#27000
b10000 V
b111101000 W
b101011110100010 1
b101011110100010 Q
b101011110100010 !"
b101011110100010 #"
b101011110100010 7
b101011110100010 >
b101011110100010 ?
b101011110100010 c
b101011110100010 $
b101011110100010 e
b101011110100010 s
b101011110100010 9
b101011110100010 <
b101011110100010 +
b101011110100010 h
b0 8
b0 =
b101011110100010 %"
b101011110100010 z
b1 2
b1 H
b1 ""
b1010111101000100000000000000000010101111010001000000000000000000000000000000000000000000000000001010111101000100000000000000000000000000000000000000000000000000101011110100010 ("
b0 $"
b100 &"
b100 :
b100 ;
b0 }
b0 /
b0 R
b101011110100010 r
b0 t
b100 I
b10000001000000 w
b1000000 '
b1000000 E
b1000000 p
b0 O
b101011110100010 #
b101011110100010 f
b11111 3
b11111 M
b11111 ]
b1 5
b1 K
b1 [
b0 %
b0 b
b0 G
b11111 C
b0 A
b100011 F
b11111000010000100000100011 @
b11111000010000100000100011 ^
b111110000100001000001000110000001111100001000010000010001100000011111000010000100000100011 )"
b11111000010000100000100011 x
b11000000100100 a
b11000000100100 S
b11000000100100 `
b11000000101000 l
b11111000010000100000100011 )
b11111000010000100000100011 i
b110000001001000000000000000000001100000010010000000000000000000011000000100100 '"
b11000000100100 v
b11000000100000 k
b11111000010000100000100011000000000000000000110000001001000000000000000000010101111010001000000000000000000000000000000000000000000000000000000000000000000000000000000000010101111010001000000000000000000000000000000000 n
b11000000100100 &
b11000000100100 m
1!
#28000
0!
